napari_segment_everything/__init__.py
napari_segment_everything/interactive_launch.py
napari_segment_everything/napari.yaml
napari_segment_everything/sam_helper.py
napari_segment_everything/segment_everything.py
napari_segment_everything/widgets.py
napari_segment_everything/_tests/__init__.py
napari_segment_everything/_tests/test_mobile_sam.py
napari_segment_everything/_tests/test_widget.py
napari_segment_everything/minimal_detection/__init__.py
napari_segment_everything/minimal_detection/detect_and_segment.py
napari_segment_everything/minimal_detection/prompt_generator.py
napari_segment_everything/minimal_detection/PromptGuidedDecoder/Prompt_guided_Mask_Decoder.pt
napari_segment_everything/minimal_detection/efficientvit/__init__.py
napari_segment_everything/minimal_detection/efficientvit/cls_model_zoo.py
napari_segment_everything/minimal_detection/efficientvit/sam_model_zoo.py
napari_segment_everything/minimal_detection/efficientvit/seg_model_zoo.py
napari_segment_everything/minimal_detection/efficientvit/apps/__init__.py
napari_segment_everything/minimal_detection/efficientvit/apps/setup.py
napari_segment_everything/minimal_detection/efficientvit/apps/data_provider/__init__.py
napari_segment_everything/minimal_detection/efficientvit/apps/data_provider/base.py
napari_segment_everything/minimal_detection/efficientvit/apps/data_provider/augment/__init__.py
napari_segment_everything/minimal_detection/efficientvit/apps/data_provider/augment/bbox.py
napari_segment_everything/minimal_detection/efficientvit/apps/data_provider/augment/color_aug.py
napari_segment_everything/minimal_detection/efficientvit/apps/data_provider/random_resolution/__init__.py
napari_segment_everything/minimal_detection/efficientvit/apps/data_provider/random_resolution/_data_loader.py
napari_segment_everything/minimal_detection/efficientvit/apps/data_provider/random_resolution/_data_worker.py
napari_segment_everything-0.1.7.dist-info/licenses/LICENSE
napari_segment_everything-0.1.7.dist-info/METADATA
napari_segment_everything-0.1.7.dist-info/WHEEL
napari_segment_everything-0.1.7.dist-info/entry_points.txt
napari_segment_everything-0.1.7.dist-info/top_level.txt
napari_segment_everything-0.1.7.dist-info/RECORD
