Metadata-Version: 2.4
Name: napari-segment-everything
Version: 0.1.7
Summary: A Napari SAM plugin to segment everything in your image (not just some things)
Home-page: https://github.com/True-North-Intelligent-Algorithms/napari-segment-everything
Author: Brian Northan, Ian Coccimiglio
Author-email: bnorthan@gmail.com
License: BSD-3-Clause
Classifier: Development Status :: 2 - Pre-Alpha
Classifier: Framework :: napari
Classifier: Intended Audience :: Developers
Classifier: License :: OSI Approved :: BSD License
Classifier: Operating System :: OS Independent
Classifier: Programming Language :: Python
Classifier: Programming Language :: Python :: 3
Classifier: Programming Language :: Python :: 3 :: Only
Classifier: Programming Language :: Python :: 3.9
Classifier: Programming Language :: Python :: 3.10
Classifier: Topic :: Scientific/Engineering :: Image Processing
Requires-Python: >=3.9
License-File: LICENSE
Requires-Dist: numpy
Requires-Dist: torch
Requires-Dist: torchvision
Requires-Dist: segment-anything
Requires-Dist: magicgui
Requires-Dist: qtpy
Requires-Dist: scikit-image
Requires-Dist: napari
Requires-Dist: gdown
Requires-Dist: opencv-python
Requires-Dist: timm
Requires-Dist: torchpack
Requires-Dist: onnx
Requires-Dist: onnxsim
Requires-Dist: matplotlib
Provides-Extra: testing
Requires-Dist: tox; extra == "testing"
Requires-Dist: pytest; extra == "testing"
Requires-Dist: pytest-cov; extra == "testing"
Requires-Dist: pytest-qt; extra == "testing"
Requires-Dist: napari; extra == "testing"
Requires-Dist: pyqt5; extra == "testing"
Dynamic: license-file
